{"project.leave_feedback":"M\u00f6chtest du feedback lassen?","projects.title":"Meine Projekte","admin.backend":"Backend","login.login":"Einloggen","login.register":"Registrieren","login.password":"Passwort","login.username":"Nutzername","login.need_account":"Brauchst du ein Konto?","login.has_account":"Hast du bereit ein Konto?","user.not_logged_in":"Nicht eingeloggt","login.repeat_password":"Passwort wiederholen","profile.edit_about":"Hier klicken um deine Beschreibung zu \u00e4ndern","profile.gravatar_email":"Bitte gib deine Gravatar Email ein","feedback.leave_feedback":"Feedback schreiben","feedback.read_feedback":"Feedback lesen","feedback.links":"Guck es dir auf dem <a href=\":url:\" class=\"project--links--link\">live Server<\/a> an oder fork es dir auf <a href=\"https:\/\/github.com\/xNocken\/:github:\" class=\"project--links--link\">Github<\/a>","login.logout":"Ausloggen","profile.profile":"Profil","404.not_found":":path: wurde nicht gefunden","feedback.no_feedback":"Es wurde noch kein Feedback geschrieben","videos.error":"Fehler beim Laden der Videos","videos.title":"Neuste Videos","profile.no_about":"Keine Beschreibung gesetzt","project.color_changer.desc":"Mein erstes Projekt was ich gemacht habe. Angefangen hat es als eine simple Crud Anwendung und hat dann \u00fcber die Zeit weitere Features bekommen"}